gpt_multi_atomic_agents/__init__.py
gpt_multi_atomic_agents/agent_definition.py
gpt_multi_atomic_agents/blackboard.py
gpt_multi_atomic_agents/blackboard_accessor.py
gpt_multi_atomic_agents/blackboard_serde.py
gpt_multi_atomic_agents/config.py
gpt_multi_atomic_agents/functions_dto.py
gpt_multi_atomic_agents/graphql_dto.py
gpt_multi_atomic_agents/main_generator.py
gpt_multi_atomic_agents/main_restapi.py
gpt_multi_atomic_agents/main_router.py
gpt_multi_atomic_agents/prompts_agent_functions.py
gpt_multi_atomic_agents/prompts_agent_graphql.py
gpt_multi_atomic_agents/prompts_router.py
gpt_multi_atomic_agents/repl_commands.py
gpt_multi_atomic_agents/rest_api_examples.py
gpt_multi_atomic_agents/system_prompt_builders.py
gpt_multi_atomic_agents/util_ai.py
gpt_multi_atomic_agents/util_graphql.py
gpt_multi_atomic_agents/util_output.py
gpt_multi_atomic_agents/util_print_agent.py
gpt_multi_atomic_agents/util_pydantic.py
gpt_multi_atomic_agents-0.7.4.dist-info/LICENSE
gpt_multi_atomic_agents-0.7.4.dist-info/METADATA
gpt_multi_atomic_agents-0.7.4.dist-info/WHEEL
gpt_multi_atomic_agents-0.7.4.dist-info/RECORD
