Metadata-Version: 2.1
Name: gpt-multi-atomic-agents
Version: 0.7.4
Summary: Combine multiple graphql-based or function-based agents with dynamic routing - based on atomic-agents.
Home-page: https://github.com/mrseanryan/gpt-multi-atomic-agents
License: MIT
Keywords: python,ai,artificial-intelligence,multi-agent,openai,multi-agent-systems,openai-api,large-language-models,llm,large-language-model,genai,genai-chatbot
Author: Sean Ryan
Author-email: mr.sean.ryan@gmail.com
Requires-Python: >=3.11,<4.0
Classifier: Development Status :: 3 - Alpha
Classifier: Environment :: Console
Classifier: Intended Audience :: Developers
Classifier: License :: OSI Approved :: MIT License
Classifier: Operating System :: OS Independent
Classifier: Programming Language :: Python
Classifier: Programming Language :: Python :: 3
Classifier: Programming Language :: Python :: 3.11
Classifier: Programming Language :: Python :: 3.12
Classifier: Topic :: Software Development :: Libraries :: Python Modules
Requires-Dist: anthropic[bedrock] (>=0.39.0,<0.40.0)
Requires-Dist: atomic-agents (>=1.0.15,<2.0.0)
Requires-Dist: cornsnake (>=0.0.74,<0.0.75)
Requires-Dist: fastapi[standard] (>=0.115.6,<0.116.0)
Requires-Dist: groq (>=0.11.0,<0.12.0)
Requires-Dist: instructor (>=1.6.3,<2.0.0)
Requires-Dist: openai (>=1.54.3,<2.0.0)
Requires-Dist: pydantic (>=2.9.2,<3.0.0)
Requires-Dist: requests (>=2.32.3,<3.0.0)
Requires-Dist: rich (>=13.9.4,<14.0.0)
Project-URL: Documentation, https://github.com/mrseanryan/gpt-multi-atomic-agents
Project-URL: Repository, https://github.com/mrseanryan/gpt-multi-atomic-agents
